uipath_enhanced_reframework_generator/__init__.py
uipath_enhanced_reframework_generator/__main__.py
uipath_enhanced_reframework_generator/enhanced_reframework_generator.py
uipath_enhanced_reframework_generator-0.0.5.dist-info/LICENSE
uipath_enhanced_reframework_generator-0.0.5.dist-info/METADATA
uipath_enhanced_reframework_generator-0.0.5.dist-info/WHEEL
uipath_enhanced_reframework_generator-0.0.5.dist-info/top_level.txt
uipath_enhanced_reframework_generator-0.0.5.dist-info/RECORD
