Metadata-Version: 2.1
Name: uipath-enhanced-reframework-generator
Version: 0.0.5
Summary: Generator to scaffold a new Enhanced REFramework project.
Home-page: https://github.com/christianblandford/UiPath-Scaffold
Author: Christian Blandford
Author-email: christianblandford@me.com
License: UNKNOWN
Platform: UNKNOWN
Classifier: Programming Language :: Python :: 3
Classifier: License :: OSI Approved :: MIT License
Classifier: Operating System :: OS Independent
Requires-Dist: console-functions (>=0.0.8)
Requires-Dist: uipath-scaffold (>=0.0.1)
Requires-Dist: uipath-scaffold-generator (>=0.0.1)
Requires-Dist: uipath (>=0.0.1)
